conda_smithy/__init__.py
conda_smithy-0.0.0.dist-info/METADATA
conda_smithy-0.0.0.dist-info/WHEEL
conda_smithy-0.0.0.dist-info/top_level.txt
conda_smithy-0.0.0.dist-info/RECORD
