Metadata-Version: 2.2
Name: conda-smithy
Version: 0.0.0
Summary: The tool for managing conda-forge feedstocks.
Project-URL: repository, https://github.com/conda-forge/conda-smithy
Requires-Python: >=3.9
